sataid/__init__.py
sataid/colormaps.py
sataid/core.py
sataid/reader.py
sataid/utils.py
sataid-1.0.1.dist-info/METADATA
sataid-1.0.1.dist-info/WHEEL
sataid-1.0.1.dist-info/RECORD
