Metadata-Version: 2.4
Name: sataid
Version: 1.0.1
Summary: A Python package for reading and visualizing SATAID binary satellite data (Himawari, etc.).
Project-URL: Homepage, https://github.com/sepriando/sataid
Project-URL: Repository, https://github.com/sepriando/sataid
Author-email: Sepriando <meteo.go@gmail.com>
License: MIT
Keywords: himawari,meteorology,sataid,satellite,visualization,weather
Classifier: Development Status :: 4 - Beta
Classifier: Intended Audience :: Science/Research
Classifier: License :: OSI Approved :: MIT License
Classifier: Programming Language :: Python :: 3
Classifier: Programming Language :: Python :: 3.8
Classifier: Programming Language :: Python :: 3.9
Classifier: Programming Language :: Python :: 3.10
Classifier: Programming Language :: Python :: 3.11
Classifier: Programming Language :: Python :: 3.12
Classifier: Programming Language :: Python :: 3.13
Classifier: Topic :: Scientific/Engineering :: Atmospheric Science
Classifier: Topic :: Scientific/Engineering :: Visualization
Requires-Python: >=3.8
Requires-Dist: cartopy
Requires-Dist: matplotlib
Requires-Dist: numpy
Provides-Extra: all
Requires-Dist: netcdf4; extra == 'all'
Requires-Dist: rasterio; extra == 'all'
Requires-Dist: scipy; extra == 'all'
Requires-Dist: xarray; extra == 'all'
Provides-Extra: netcdf
Requires-Dist: netcdf4; extra == 'netcdf'
